LICENSE
MANIFEST.in
README.md
setup.cfg
setup.py
django_slick_admin/__init__.py
django_slick_admin/settings.py
django_slick_admin.egg-info/PKG-INFO
django_slick_admin.egg-info/SOURCES.txt
django_slick_admin.egg-info/dependency_links.txt
django_slick_admin.egg-info/not-zip-safe
django_slick_admin.egg-info/requires.txt
django_slick_admin.egg-info/top_level.txt
django_slick_admin/static/admin/img/icon-no.svg
django_slick_admin/static/admin/img/icon-yes.svg
django_slick_admin/static/django_slick_admin/css/cms-styles.css
django_slick_admin/static/django_slick_admin/css/django-slick-admin.css
django_slick_admin/static/django_slick_admin/fonts/MaterialIcons-Regular.eot
django_slick_admin/static/django_slick_admin/fonts/MaterialIcons-Regular.svg
django_slick_admin/static/django_slick_admin/fonts/MaterialIcons-Regular.ttf
django_slick_admin/static/django_slick_admin/fonts/MaterialIcons-Regular.woff
django_slick_admin/static/django_slick_admin/fonts/MaterialIcons-Regular.woff2
django_slick_admin/static/django_slick_admin/fonts/django-admin-iconfont.eot
django_slick_admin/static/django_slick_admin/fonts/django-admin-iconfont.svg
django_slick_admin/static/django_slick_admin/fonts/django-admin-iconfont.ttf
django_slick_admin/static/django_slick_admin/fonts/django-admin-iconfont.woff
django_slick_admin/static/django_slick_admin/fonts/django-admin-iconfont.woff2
django_slick_admin/static/django_slick_admin/img/bg-pattern-light.jpg
django_slick_admin/static/django_slick_admin/img/bg-pattern.jpg
django_slick_admin/static/django_slick_admin/img/django-cms-logo.png
django_slick_admin/static/django_slick_admin/img/drag-light.png
django_slick_admin/static/django_slick_admin/img/drag-norepeat.png
django_slick_admin/static/django_slick_admin/img/drag.png
django_slick_admin/static/django_slick_admin/img/icon_addlink@2x.gif
django_slick_admin/static/django_slick_admin/img/icon_addlink_large.gif
django_slick_admin/static/django_slick_admin/img/icon_addlink_large@2x.gif
django_slick_admin/static/django_slick_admin/img/icon_arrow_down.png
django_slick_admin/static/django_slick_admin/img/icon_arrow_right.png
django_slick_admin/static/django_slick_admin/img/icon_calendar@2x.gif
