Metadata-Version: 1.1
Name: django-slick-admin
Version: 0.1.4
Summary: Slick admin styles for Django and django CMS.
Home-page: https://github.com/palmbeach-interactive/django-slick-admin/
Author: Marc Widmer, Jonas Ohrstrom
Author-email: marc@pbi.io, jonas@pbi.io
License: MIT License
Platform: OS Independent
Classifier: Environment :: Web Environment
Classifier: Framework :: Django
Classifier: Intended Audience :: Developers
Classifier: License :: OSI Approved :: MIT License
Classifier: Operating System :: OS Independent
Classifier: Programming Language :: Python
Classifier: Programming Language :: Python :: 2
Classifier: Programming Language :: Python :: 3
